cisformer/__init__.py
cisformer/atac2rna_predict.py
cisformer/atac2rna_surround_attention_generate.py
cisformer/atac2rna_train.py
cisformer/compute_surround_enhancer.py
cisformer/data_preprocess.py
cisformer/generate_default_config.py
cisformer/map_rna_atac.py
cisformer/rna2atac_predict.py
cisformer/rna2atac_train.py
cisformer/runner.py
cisformer/M2Mmodel/M2M.py
cisformer/M2Mmodel/__init__.py
cisformer/M2Mmodel/block.py
cisformer/M2Mmodel/utils.py
cisformer/resource/.__init__.py
cisformer/resource/hg38.refGene.gtf.gz
cisformer/resource/human_cCREs.bed
cisformer/resource/human_genes.tsv
cisformer-1.0.1.dist-info/METADATA
cisformer-1.0.1.dist-info/WHEEL
cisformer-1.0.1.dist-info/entry_points.txt
cisformer-1.0.1.dist-info/licenses/LICENCE
cisformer-1.0.1.dist-info/RECORD
