Metadata-Version: 2.4
Name: cisformer
Version: 1.0.1
Summary: Cisformer command-line tools
Project-URL: Homepage, https://github.com/wanglabtongji/Cisformer
Project-URL: Issues, https://github.com/qihang-zou/Cisformer/issues
Author-email: Chenfei Wang <08chenfeiwang@tongji.edu.cn>
License-Expression: MIT
License-File: LICENCE
Classifier: Operating System :: OS Independent
Classifier: Programming Language :: Python :: 3
Requires-Python: >=3.9
